InstruHub/__init__.py
InstruHub/_version.py
InstruHub/directories.py
InstruHub/client/__init__.py
InstruHub/instrument/__init__.py
InstruHub/instrument/base.py
InstruHub/instrument/Alazar/__init__.py
InstruHub/instrument/NI/__init__.py
InstruHub/instrument/NI/ni_daq.py
InstruHub/instrument/Tektronix/__init__.py
InstruHub/utils/__init__.py
InstruHub/utils/device_manager.py
instruhub-0.0.2.dist-info/licenses/LICENSE
instruhub-0.0.2.dist-info/METADATA
instruhub-0.0.2.dist-info/WHEEL
instruhub-0.0.2.dist-info/top_level.txt
instruhub-0.0.2.dist-info/RECORD
