Metadata-Version: 2.4
Name: InstruHub
Version: 0.0.2
Summary: A package for managing multiple lab instruments for data acquisition, galvo control, and data processing.
Author-email: Martin Poinsinet de Sivry-Houle <martin.poinsinet.de.sivry@gmail.com>
License: MIT License
Keywords: instrument,acquisition
Classifier: Programming Language :: Python :: 3
Classifier: License :: OSI Approved :: MIT License
Classifier: Operating System :: OS Independent
Requires-Python: >=3.11
License-File: LICENSE
Requires-Dist: nidaqmx>=0.7.0
Requires-Dist: matplotlib>=3.0.0
Requires-Dist: numpy>=1.19.0
Provides-Extra: testing
Requires-Dist: pytest<9.0,>=7.4; extra == "testing"
Requires-Dist: pytest-cov<6,>=2; extra == "testing"
Requires-Dist: pytest-json-report~=1.5; extra == "testing"
Requires-Dist: coverage~=7.6; extra == "testing"
Provides-Extra: documentation
Requires-Dist: numpydoc==1.6.0; extra == "documentation"
Requires-Dist: sphinx>=5.1.1; extra == "documentation"
Requires-Dist: sphinx-gallery==0.15.0; extra == "documentation"
Requires-Dist: sphinx-rtd-theme==2.0.0; extra == "documentation"
Requires-Dist: pydata-sphinx-theme==0.14.1; extra == "documentation"
Provides-Extra: dev
Requires-Dist: flake8==7.1.1; extra == "dev"
Dynamic: license-file
